assdialoguemerger/__init__.py
assdialoguemerger/assdialoguemerger.py
assdialoguemerger/cli.py
assDialogueMerger-0.1.dist-info/LICENSE
assDialogueMerger-0.1.dist-info/METADATA
assDialogueMerger-0.1.dist-info/WHEEL
assDialogueMerger-0.1.dist-info/entry_points.txt
assDialogueMerger-0.1.dist-info/top_level.txt
assDialogueMerger-0.1.dist-info/RECORD
