Metadata-Version: 2.1
Name: assDialogueMerger
Version: 0.1
Summary: Merges the dialogue of one subtitle into the timings of another, similar subtitle
Author: royvds
License: GNU GENERAL PUBLIC LICENSE
Project-URL: Homepage, https://github.com/royvds/assDialogueMerger/
Project-URL: Bug Tracker, https://github.com/royvds/assDialogueMerger/issues
Classifier: Programming Language :: Python :: 3.9
Classifier: License :: OSI Approved :: GNU General Public License v3 (GPLv3)
Classifier: Operating System :: OS Independent
Requires-Python: >=3.9
License-File: LICENSE
